gguf_web/__init__.py
gguf_web/static/index.html
gguf_web/static/logo.png
gguf_web/static/materialdesignicons.min.css
gguf_web/static/user.css
gguf_web/static/assets/BaseViewTemplate-BTbuZf5t.js
gguf_web/static/assets/CREDIT.txt
gguf_web/static/assets/DesktopStartView-D9r53Bue.js
gguf_web/static/assets/DesktopUpdateView-C-R0415K.js
gguf_web/static/assets/DesktopUpdateView-CxchaIvw.css
gguf_web/static/assets/DownloadGitView-PWqK5ke4.js
gguf_web/static/assets/ExtensionPanel-Ba57xrmg.js
gguf_web/static/assets/GraphView-B_UDZi95.js
gguf_web/static/assets/GraphView-Bo28XDd0.css
gguf_web/static/assets/InstallView-DW9xwU_F.js
gguf_web/static/assets/InstallView-DbJ2cGfL.css
gguf_web/static/assets/KeybindingPanel-CDYVPYDp.css
gguf_web/static/assets/KeybindingPanel-oavhFdkz.js
gguf_web/static/assets/MaintenanceView-Bh8OZpgl.js
gguf_web/static/assets/MaintenanceView-DEJCj8SR.css
gguf_web/static/assets/ManualConfigurationView-CsirlNfV.css
gguf_web/static/assets/ManualConfigurationView-DTLyJ3VG.js
gguf_web/static/assets/MetricsConsentView-C80fk2cl.js
gguf_web/static/assets/NotSupportedView-B78ZVR9Z.js
gguf_web/static/assets/NotSupportedView-RFx6eCkN.css
gguf_web/static/assets/ServerConfigPanel-BYrt6wyr.js
gguf_web/static/assets/ServerStartView-B7TlHxYo.js
gguf_web/static/assets/ServerStartView-BZ7uhZHv.css
gguf_web/static/assets/TerminalOutputDrawer-CKr7Br7O.js
gguf_web/static/assets/UserSelectView-C703HOyO.js
gguf_web/static/assets/WelcomeView-Brz3-luE.css
gguf_web/static/assets/WelcomeView-DIFvbWc2.js
gguf_web/static/assets/index-A_bXPJCN.js
gguf_web/static/assets/index-B36GcHVN.js
gguf_web/static/assets/index-BRhY6FpL.css
gguf_web/static/assets/index-Bv0b06LE.js
gguf_web/static/assets/index-C068lYT4.js
gguf_web/static/assets/index-CBxvvAzM.css
gguf_web/static/assets/index-CgMyWf7n.js
gguf_web/static/assets/index-Dzu9WL4p.js
gguf_web/static/assets/index-SeIZOWJp.js
gguf_web/static/assets/keybindingService-DyjX-nxF.js
gguf_web/static/assets/primeicons-C6QP2o4f.woff2
gguf_web-0.0.2.dist-info/LICENSE
gguf_web-0.0.2.dist-info/WHEEL
gguf_web-0.0.2.dist-info/METADATA
gguf_web-0.0.2.dist-info/RECORD
