Metadata-Version: 2.1
Name: gguf-web
Version: 0.0.2
Summary: gguf web (frontend)
Author-email: calcuis <info@calcu.io>
Classifier: License :: OSI Approved :: MIT License
Project-URL: GitHub, https://github.com/calcuis/gguf-web
Project-URL: Homepage, https://gguf.org
